PCBpy/__init__.py
PCBpy-0.0.1.dist-info/METADATA
PCBpy-0.0.1.dist-info/RECORD
PCBpy-0.0.1.dist-info/WHEEL
PCBpy-0.0.1.dist-info/top_level.txt
